packmetric/__init__.py
packmetric/packmetric.py
packmetric/metrics/__init__.py
packmetric/metrics/base_metrics.py
packmetric/utils/__init__.py
packmetric/utils/lightning_callback.py
packmetric/utils/template.py
packmetric-0.1.2.dist-info/LICENSE
packmetric-0.1.2.dist-info/METADATA
packmetric-0.1.2.dist-info/WHEEL
packmetric-0.1.2.dist-info/top_level.txt
packmetric-0.1.2.dist-info/RECORD
