Metadata-Version: 2.2
Name: packmetric
Version: 0.1.2
Summary: PackMetric
Author-email: e_yi <e_yi@outlook.com>
Project-URL: Repository, https://github.com/e-yi/packmetric.git
Project-URL: Issues, https://github.com/e-yi/packmetric/issues
Project-URL: Changelog, https://github.com/e-yi/packmetric/blob/master/CHANGELOG.md
Requires-Python: >=3.7
License-File: LICENSE
Requires-Dist: lightning>=2
Requires-Dist: torch>=2.0.0
Requires-Dist: torchmetrics>1.3.0
